COPYING
MANIFEST.in
README
health_gyneco_view.xml
setup.py
./__init__.py
./health_gyneco.py
./health_gyneco_view.xml
./tryton.cfg
./doc/index.rst
./locale/ar.po
./locale/de.po
./locale/el.po
./locale/es.po
./locale/fr.po
./locale/it_IT.po
./locale/ja_JP.po
./locale/lo.po
./locale/pt_BR.po
./locale/zh_CN.po
./security/access_rights.xml
./tests/__init__.py
./tests/test_health_gyneco.py
./view/gnuhealth_colposcopy_history.xml
./view/gnuhealth_colposcopy_history_tree.xml
./view/gnuhealth_mammography_history.xml
./view/gnuhealth_mammography_history_tree.xml
./view/gnuhealth_menstrual_history.xml
./view/gnuhealth_menstrual_history_tree.xml
./view/gnuhealth_pap_history.xml
./view/gnuhealth_pap_history_tree.xml
./view/gnuhealth_patient.xml
./view/gnuhealth_patient_pregnancy.xml
./view/gnuhealth_patient_pregnancy_tree.xml
./view/gnuhealth_perinatal.xml
./view/gnuhealth_perinatal_monitor.xml
./view/gnuhealth_perinatal_monitor_tree.xml
./view/gnuhealth_perinatal_tree.xml
./view/gnuhealth_prenatal_evaluation.xml
./view/gnuhealth_prenatal_evaluation_tree.xml
./view/gnuhealth_puerperium_monitor.xml
./view/gnuhealth_puerperium_monitor_tree.xml
locale/ar.po
locale/de.po
locale/el.po
locale/es.po
locale/fr.po
locale/it_IT.po
locale/ja_JP.po
locale/lo.po
locale/pt_BR.po
locale/zh_CN.po
security/access_rights.xml
trytond_health_gyneco.egg-info/PKG-INFO
trytond_health_gyneco.egg-info/SOURCES.txt
trytond_health_gyneco.egg-info/dependency_links.txt
trytond_health_gyneco.egg-info/entry_points.txt
trytond_health_gyneco.egg-info/not-zip-safe
trytond_health_gyneco.egg-info/requires.txt
trytond_health_gyneco.egg-info/top_level.txt
view/gnuhealth_colposcopy_history.xml
view/gnuhealth_colposcopy_history_tree.xml
view/gnuhealth_mammography_history.xml
view/gnuhealth_mammography_history_tree.xml
view/gnuhealth_menstrual_history.xml
view/gnuhealth_menstrual_history_tree.xml
view/gnuhealth_pap_history.xml
view/gnuhealth_pap_history_tree.xml
view/gnuhealth_patient.xml
view/gnuhealth_patient_pregnancy.xml
view/gnuhealth_patient_pregnancy_tree.xml
view/gnuhealth_perinatal.xml
view/gnuhealth_perinatal_monitor.xml
view/gnuhealth_perinatal_monitor_tree.xml
view/gnuhealth_perinatal_tree.xml
view/gnuhealth_prenatal_evaluation.xml
view/gnuhealth_prenatal_evaluation_tree.xml
view/gnuhealth_puerperium_monitor.xml
